safulate/__init__.py
safulate/__main__.py
safulate/_version.py
safulate/asts.py
safulate/cli.py
safulate/environment.py
safulate/errors.py
safulate/interpreter.py
safulate/lexer.py
safulate/mock.py
safulate/native_context.py
safulate/parser.py
safulate/properties.py
safulate/py_libs.py
safulate/tokens.py
safulate/values.py
safulate/libs/_msgspec_wrapper.py
safulate/libs/builtins.py
safulate/libs/hello.py
safulate/libs/json.py
safulate/libs/regex.py
safulate/libs/toml.py
safulate/libs/types.py
safulate/libs/yaml.py
safulate-0.1.0.dist-info/licenses/LICENSE
safulate-0.1.0.dist-info/METADATA
safulate-0.1.0.dist-info/WHEEL
safulate-0.1.0.dist-info/entry_points.txt
safulate-0.1.0.dist-info/top_level.txt
safulate-0.1.0.dist-info/RECORD
